[
  {

    "id": "1",
    "label": "Keynote 1",
    "start": "11/20/21 09:00:00",
    "end": "11/20/21 09:00:00",
    "conf": "devprconf2021",
    "talk": "1"
  },
  {
    "id": "2",
    "label": "BEMUG",
    "start": "11/20/21 10:00:00",
    "end": "11/20/21 10:00:00",
    "conf": "devprconf2021",
    "talk": "1"
  },
  {
    "id": "3",
    "label": "Agile MGA",
    "start": "11/20/21 10:00:00",
    "end": "11/20/21 10:00:00",
    "conf": "devprconf2021",
    "talk": "1"
  },
  {
    "id": "4",
    "label": "lxDA",
    "start": "11/20/21 10:00:00",
    "end": "11/20/21 10:00:00",
    "conf": "devprconf2021",
    "talk": "1"
  },
  {
    "id": "5",
    "label": "Agile MGA 2",
    "start": "11/20/21 11:00:00",
    "end": "11/20/21 11:00:00",
    "conf": "devprconf2021",
    "talk": "1"
  },
  {
    "id": "6",
    "label": "DevParaná Campo Mourão",
    "start": "11/20/21 11:00:00",
    "end": "11/20/21 11:00:00",
    "conf": "devprconf2021",
    "talk": "1"
  },
  {
    "id": "7",
    "label": "DevGirls",
    "start": "11/20/21 11:00:00",
    "end": "11/20/21 11:00:00",
    "conf": "devprconf2021",
    "talk": "1"
  },
  {
    "id": "8",
    "label": "Almoço",
    "start": "11/20/21 12:00:00",
    "end": "11/20/21 12:00:00",
    "conf": "devprconf2021",
    "talk": "1"
  },
  {
    "id": "9",
    "label": "DevOps Maringá",
    "start": "11/20/21 13:30:00",
    "end": "11/20/21 13:30:00",
    "conf": "devprconf2021",
    "talk": "1"
  },
  {
    "id": "10",
    "label": "Front In Maringá",
    "start": "11/20/21 13:30:00",
    "end": "11/20/21 13:30:00",
    "conf": "devprconf2021",
    "talk": "1"
  },
  {
    "id": "11",
    "label": "DevCia",
    "start": "11/20/21 13:30:00",
    "end": "11/20/21 13:30:00",
    "conf": "devprconf2021",
    "talk": "1"
  },
  {
    "id": "12",
    "label": "Ingá PHP",
    "start": "11/20/21 14:30:00",
    "end": "11/20/21 14:30:00",
    "conf": "devprconf2021",
    "talk": "1"
  },
  {
    "id": "13",
    "label": "GDG Cascavel",
    "start": "11/20/21 14:30:00",
    "end": "11/20/21 14:30:00",
    "conf": "devprconf2021",
    "talk": "1"
  },
  {
    "id": "14",
    "label": "GDG Toledo",
    "start": "11/20/21 14:30:00",
    "end": "11/20/21 14:30:00",
    "conf": "devprconf2021",
    "talk": "1"
  },
  {
    "id": "15",
    "label": "Intervalo / Coffee",
    "start": "11/20/21 15:30:00",
    "end": "11/20/21 15:30:00",
    "conf": "devprconf2021",
    "talk": "1"
  },
  {
    "id": "16",
    "label": "DevParaná Umuarama",
    "start": "11/20/21 16:00:00",
    "end": "11/20/21 16:00:00",
    "conf": "devprconf2021",
    "talk": "1"
  },
  {
    "id": "17",
    "label": "Python Maringá",
    "start": "11/20/21 16:00:00",
    "end": "11/20/21 16:00:00",
    "conf": "devprconf2021",
    "talk": "1"
  },
  {
    "id": "18",
    "label": "Afterdata",
    "start": "11/20/21 16:00:00",
    "end": "11/20/21 16:00:00",
    "conf": "devprconf2021",
    "talk": "1"
  },
  {
    "id": "19",
    "label": "Keynote 2",
    "start": "11/20/21 17:00:00",
    "end": "11/20/21 17:00:00",
    "conf": "devprconf2021",
    "talk": "1"
  }
]
